README.txt
setup.py
src/nous/__init__.py
src/nous.migration.egg-info/PKG-INFO
src/nous.migration.egg-info/SOURCES.txt
src/nous.migration.egg-info/dependency_links.txt
src/nous.migration.egg-info/entry_points.txt
src/nous.migration.egg-info/not-zip-safe
src/nous.migration.egg-info/requires.txt
src/nous.migration.egg-info/top_level.txt
src/nous/migration/__init__.py
src/nous/migration/add_script.py
src/nous/migration/tests.py