Metadata-Version: 1.0
Name: nous.migration
Version: 0.7.1
Summary: Yet another sqlalchemy based database schema migration tool
Home-page: http://github.com/nous-consulting/nous.migration/
Author: Ignas Mikalajunas
Author-email: ignas@nous.lt
License: GPL
Platform: UNKNOWN
Classifier: Development Status :: 4 - Beta
Classifier: Intended Audience :: Developers
Classifier: License :: OSI Approved :: GNU General Public License (GPL)
Classifier: Programming Language :: Python
